MANIFEST.in
README.txt
setup.cfg
setup.py
docs/HISTORY.txt
docs/INSTALL.txt
docs/LICENSE.GPL
docs/LICENSE.txt
quintagroup/__init__.py
quintagroup.portlet.static.egg-info/PKG-INFO
quintagroup.portlet.static.egg-info/SOURCES.txt
quintagroup.portlet.static.egg-info/dependency_links.txt
quintagroup.portlet.static.egg-info/entry_points.txt
quintagroup.portlet.static.egg-info/namespace_packages.txt
quintagroup.portlet.static.egg-info/not-zip-safe
quintagroup.portlet.static.egg-info/requires.txt
quintagroup.portlet.static.egg-info/top_level.txt
quintagroup/portlet/__init__.py
quintagroup/portlet/static/README.txt
quintagroup/portlet/static/__init__.py
quintagroup/portlet/static/configlet.txt
quintagroup/portlet/static/configure.zcml
quintagroup/portlet/static/staticstylishportlet.pt
quintagroup/portlet/static/staticstylishportlet.py
quintagroup/portlet/static/utils.py
quintagroup/portlet/static/vocabularies.py
quintagroup/portlet/static/browser/__init__.py
quintagroup/portlet/static/browser/configlet.py
quintagroup/portlet/static/browser/configure.zcml
quintagroup/portlet/static/locales/quintagroup.portlet.static.pot
quintagroup/portlet/static/profiles/default/controlpanel.xml
quintagroup/portlet/static/profiles/default/metadata.xml
quintagroup/portlet/static/profiles/default/portlets.xml
quintagroup/portlet/static/profiles/default/propertiestool.xml
quintagroup/portlet/static/tests/__init__.py
quintagroup/portlet/static/tests/base.py
quintagroup/portlet/static/tests/test_configlet.py
quintagroup/portlet/static/tests/test_portlet.py