Metadata-Version: 1.0
Name: quintagroup.portlet.static
Version: 0.5
Summary: Static portlet with one extra styling field
Home-page: http://svn.quintagroup.com/products/quintagroup.portlet.static
Author: Quintagroup
Author-email: support@quintagroup.com
License: GPL
Keywords: plone static portlet
Platform: UNKNOWN
Classifier: Framework :: Plone
Classifier: Programming Language :: Python
Classifier: Topic :: Software Development :: Libraries :: Python Modules
